README.txt
setup.py
src/rsl/__init__.py
src/rsl.rest.egg-info/PKG-INFO
src/rsl.rest.egg-info/SOURCES.txt
src/rsl.rest.egg-info/dependency_links.txt
src/rsl.rest.egg-info/entry_points.txt
src/rsl.rest.egg-info/namespace_packages.txt
src/rsl.rest.egg-info/requires.txt
src/rsl.rest.egg-info/top_level.txt
src/rsl/rest/__init__.py
src/rsl/rest/factories.py
src/rsl/rest/rest.py
