Metadata-Version: 1.0
Name: rsl.rest
Version: 0.2.0
Summary: Remote Service Library REST module
Home-page: http://sourceforge.net/projects/rslib/
Author: Gerhard Weis
Author-email: gerhard.weis@proclos.com
License: BSD-like
Platform: UNKNOWN
Classifier: Development Status :: 3 - Alpha
Classifier: Environment :: Web Environment
Classifier: Intended Audience :: Developers
Classifier: License :: OSI Approved :: BSD License
Classifier: Operating System :: OS Independent
Classifier: Programming Language :: Python
Classifier: Topic :: Internet
Classifier: Topic :: Software Development :: Libraries :: Python Modules
Classifier: Topic :: System :: Networking
